auto_behave/__init__.py
auto_behave/directive.py
auto_behave/gen_step_rst.py
auto_behave/handlers.py
auto_behave/node.py
auto_behave/templates/behave.html
auto_behave-0.0.7.dist-info/DESCRIPTION.rst
auto_behave-0.0.7.dist-info/METADATA
auto_behave-0.0.7.dist-info/RECORD
auto_behave-0.0.7.dist-info/WHEEL
auto_behave-0.0.7.dist-info/metadata.json
auto_behave-0.0.7.dist-info/top_level.txt
