Metadata-Version: 2.0
Name: auto-behave
Version: 0.0.7
Summary: A sphinx extension for behave to auto document
Home-page: https://github.com/publons/auto_behave
Author: Brandon Scott-Hill
Author-email: brandon.scotthill@publons.com
License: MIT License
Platform: UNKNOWN
Classifier: Intended Audience :: Developers
Classifier: License :: OSI Approved :: MIT License
Classifier: Operating System :: OS Independent
Classifier: Programming Language :: Python :: 3.6
Classifier: Topic :: Documentation :: Sphinx
Requires-Python: >=3.6
Requires-Dist: sphinx
Requires-Dist: docutils
Requires-Dist: jinja2
